setup.py
ahliang_distributions.egg-info/PKG-INFO
ahliang_distributions.egg-info/SOURCES.txt
ahliang_distributions.egg-info/dependency_links.txt
ahliang_distributions.egg-info/not-zip-safe
ahliang_distributions.egg-info/top_level.txt
distributions/Binomialdistribution.py
distributions/Gaussiandistribution.py
distributions/Generaldistribution.py
distributions/__init__.py